setup.py
django_frontserver.egg-info/PKG-INFO
django_frontserver.egg-info/SOURCES.txt
django_frontserver.egg-info/dependency_links.txt
django_frontserver.egg-info/top_level.txt
frontserver/__init__.py
frontserver/settings.py
frontserver/utils.py
frontserver/management/__init__.py
frontserver/management/commands/__init__.py
frontserver/management/commands/frontserver.py