Metadata-Version: 1.0
Name: django-frontserver
Version: 0.3.3
Summary: Run grunt/gulp watcher and django server with a single command.
Home-page: https://github.com/zenwalker/django-frontserver
Author: Maxim Poletaev
Author-email: zenwalker2@gmail.com
License: UNKNOWN
Keywords: django,gulp,grunt,frontend
Platform: UNKNOWN
